{
  "intents": [
    {
      "tag": "greeting",
      "patterns": [
        "Hi",
        "Hey",
        "How are you",
        "Is anyone there?",
        "Hello",
        "Good day"
      ],
      "responses": [
        "Hi there, what can I do for you?",
        "Hi there, how can I help you?"
      ]
    },
    {
      "tag": "goodbye",
      "patterns": [
        "Bye",
        "See you later",
        "Goodbye"
      ],
      "responses": [
        "See you later, thanks for visiting",
        "Have a nice day",
        "Bye! Come back again soon."
      ]
    },
    {
      "tag": "thanks",
      "patterns": [
        "Thanks",
        "Thank you",
        "That's helpful",
        "Thank's a lot!"
      ],
      "responses": [
        "Happy to help!",
        "Any time!",
        "My pleasure"
      ]
    },
    {
      "tag": "information/details",
      "patterns": [
        "What do you know about the Oud?",
        "Could you provide some information on the Oud?",
        "Could you give me some details about the Oud?",
        "What can you tell me about the Oud?"
      ],
      "responses": [
        "The Oud is a string instrument commonly used in Middle Eastern and North African music. It has a pear-shaped body and a short neck"
      ]
    },
    {
      "tag": "Number of strings",
      "patterns": [
        "How many strings does it have?",
        "What is the number of strings on an oud?",
        "Number of strings",
        "How many strings does an oud typically possess?",
        "What is the number of strings on an oud?"
      ],
      "responses": [
        "Traditional Ouds typically have 11 strings, though some modern versions may have fewer for simplicity."
      ]
    },
    {
      "tag": "materials ",
      "patterns": [
        "What are the the materials of an Oud?",
        "What are the primary materials involved in the making of an Oud?",
        "materials",
        "What are the usual materials utilized in manufacturing an Oud?",
        "Which materials are customary in the construction process of an Oud?"
      ],
      "responses": [
        " The body of the Oud is often made from wood, such as walnut, rosewood, or mahogany. The strings are usually made of nylon or gut."
      ]
    },
    {
      "tag": "historical",
      "patterns": [
        "What is the historical background of the Oud instrument?",
        "what is the historical background of the Oud instrument?",
        "what is the history of oud?",     
        "What is the history of oud?",   
        "history",
        "historical",
        "Can you give me an overview of how the Oud has developed throughout history?",
        "I'd like to learn more about the historical context of the Oud - could you share some information on its past?"
      ],
      "responses": [
        "The Oud has a long history, dating back thousands of years. It originated in the Middle East and is considered one of the oldest known musical instruments.",
        "Oud construction involves several steps, including shaping the body, carving the neck, fitting the pegbox, installing the soundboard and rosette, attaching the bridge, and stringing the instrument. Each step requires precision and expertise to ensure optimal sound quality and playability."
      ]
    },
    {
      "tag": "Famous players",
      "patterns": [
        "What are some famous Oud players?",
        "What are the names of some celebrated Oud players?",
        "Who are considered to be prominent figures in the world of Oud music?",
        "Famous players",
        "Could you list a few well-known individuals who excel in playing the Oud?"
      ],
      "responses": [
        " Some renowned Oud players include Munir Bashir, Marcel Khalife, and Anouar Brahem."
      ]
    },
    {
      "tag": "types of Ouds",
      "patterns": [
        "How many types of Ouds are there?",
        "What are the different types of Ouds?",
        "Can you list the diverse kinds of Ouds?",
        "Are there different classifications of Ouds?"
      ],
      "responses": [
        "There are several types of Ouds, including Turkish, Arabic, and Persian varieties. Each has its own unique characteristics in terms of size, shape, and sound."
      ]
    },
    {
      "tag": "tune of Ouds",
      "patterns": [
        "Can you explain the process of fine-tuning an Oud?",
        "What are the steps for adjusting the strings of an Oud to achieve optimal pitch?",
        "Could you provide guidance on how to accurately tune an Oud instrument?",
        "How would you go about adjusting the strings of an Oud to achieve the desired tones?"
      ],
      "responses": [
        "Ouds are typically tuned in a variety of ways, but a common tuning is C-F-A-D-G-C, with the lowest string being C. Tuning can be done using a tuning fork, electronic tuner, or by ear."
      ]
    },
    {
      "tag": "Learning Resources",
      "patterns": [
        "Can you recommend any Oud learning resources?",
        "What are some good sources for beginners wanting to learn the Oud?",
        "Can you provide me with some guidance on finding educational materials for mastering the Oud?",
        "What are some reputable Oud learning materials I can access?"
      ],
      "responses": [
        "There are many resources available, including online tutorials, instructional books, and video lessons. Websites like OudForGuitarists.com and Oud.Luthier.org offer valuable learning materials for beginners and advanced players alike."
      ]
    },
    {
      "tag": "Oud compositions",
      "patterns": [
        "What are some famous Oud compositions?",
        "What are the steps for adjusting the strings of an Oud to achieve optimal pitch?",
        "Could you provide guidance on how to accurately tune an Oud instrument?",
        "How would you go about adjusting the strings of an Oud to achieve the desired tones?"
      ],
      "responses": [
        "         Some famous Oud compositions include 'Taqsīm', 'Sama'i,' and 'Longa.' These pieces showcase the versatility and beauty of the instrument in different musical contexts."
      ]
    },
    {
      "tag": "Ouds rosette",
      "patterns": [
        "What is the significance of the rosette on an Oud?",
        "Why is the rosette important on an Oud?",
        "Ouds rosette",
        "What role does the rosette play in the design of an Oud?"
      ],
      "responses": [
        "The rosette, typically located on the soundboard of the Oud, serves MaqamOudBoth a decorative and functional purpose. It allows air to circulate inside the instrument, contributing to its resonance and projection."
      ]
    },
        {
      "tag": "Arabic vs Turkish",
      "patterns": [
        "What is the difference between Turkish and Arabic Oud?",
        "What is the difference between Arabic and Turkish Oud?",  
        "What is the difference between Turkish and an Arabic Oud?",
        "What is the difference between Arabic and Turkish Oud?",    
        "Can you explain the difference between a Turkish and an Arabic Oud?",
        "How do Turkish and Arabic Ouds differ from each other?"
      ],
      "responses": [
        "Turkish and Arabic Ouds differ in various aspects, including their tuning, construction, and playing techniques. Turkish Ouds often have a brighter sound and a smaller body, while Arabic Ouds have a deeper, more resonant tone and a larger body.",
        "The Arabic Oud generally has a smaller body and a deeper bowl, resulting in a warmer, more resonant sound. The Turkish Oud often has a larger body and a brighter tone."
      ]
    },
    {
      "tag": "main components",
      "patterns": [
        "What are the main components of an Oud?",
        "What are the essential elements that form an Oud?",
        "What are the basic building blocks of an Oud?"
      ],
      "responses": [
        "The main components of an Oud include the body, neck, pegbox, tuning pegs, strings, and bridge. Each component plays a crucial role in producing sound and facilitating playability."
      ]
    },
    {
      "tag": "Ouds musical genres",
      "patterns": [
        "Can the Oud be played in different musical genres?"
      ],
      "responses": [
        "         Yes, the Oud is a versatile instrument that can be heard in a variety of musical genres, including traditional folk music, classical compositions, jazz, fusion, and contemporary world music."
      ]
    },
    {
      "tag": "Ouds accessories",
      "patterns": [
        "What are some common Oud accessories?",
        "Which accessories are commonly paired with the Oud?",
        "Can you detail the standard accessories for an Oud musician?"
      ],
      "responses": [
        "Common Oud accessories include plectrums (called 'risha' or 'mezrap'), Oud cases or gig bags, spare strings, string winders, humidity control devices, and cleaning supplies."
      ]
    },
    {
      "tag": "learning Oud",
      "patterns": [
        "Can you recommend any Oud instructional books or method books?",
        "Do you know of any good resources for learning Oud, such as books or method guides?",
        "Do you have any favorite Oud instructional books or method guides that you could recommend?"
      ],
      "responses": [
        "Yes, there are many instructional books and method books available for learning the Oud, catering to beginners, intermediate, and advanced players. Some recommended titles include 'The Oud Method' by John Bilezikjian and 'Oud Method for Beginners' by Ahmed Mukhtar."
      ]
    },
    {
      "tag": "Oud scales",
      "patterns": [
        "What are some common Oud scales and modes?",
        "Could you provide examples of common Oud scales and modes?",
"What are the typical scale patterns utilized in oud music?"

      ],
      "responses": [
        "Common Oud scales and modes include Maqam Hijaz, Maqam Nahawand, and Maqam Bayati. These scales are used in traditional Middle Eastern music to create melodic patterns and improvisations."
      ]
    }
   ,
    {
      "tag": "main components",
      "patterns": [
        "What are the main components of an Oud?",
        "What are the primary parts that make up the Oud instrument?",
        "What are the fundamental components or features of an Oud?",
        "What are the main building blocks of an Oud, from a construction standpoint?",
        "What are the distinguishing parts that one would find on an Oud?"
      ],
      "responses": [
        "The main components of an Oud include the body, neck, pegbox, tuning pegs, strings, and soundboard."
      ]
    }    ,
    {
      "tag": "different sizes",
      "patterns": [
        "What are the different sizes of Ouds?",
        "What are the various sizes available for oud instruments?",
          "What are the sizes of Oud?",   
             "What are the size of Oud?"      
      ],
      "responses": [
        "Ouds come in various sizes, ranging from smaller, travel-sized models to larger concert-sized instruments. The size can affect the instrument's tone and playability."
      ]
    }    ,
    {
      "tag": "playing techniques?",
      "patterns": [
        ":What are some common Oud playing techniques?",
        "Can you discuss the diverse techniques involved in mastering the oud instrument"
      ],
      "responses": [
        "Common Oud playing techniques include tremolo, arpeggios, scales, slides, and glissandos, each of which adds depth and expression to the music."
      ]
    } 
  ]
}